aws_saml_auth/VERSION
aws_saml_auth/__init__.py
aws_saml_auth/amazon.py
aws_saml_auth/configuration.py
aws_saml_auth/login_server.py
aws_saml_auth/redirect_server.py
aws_saml_auth/saml.py
aws_saml_auth/util.py
aws_saml_auth/tests/__init__.py
aws_saml_auth/tests/test_amazon.py
aws_saml_auth/tests/test_args_parser.py
aws_saml_auth/tests/test_config_parser.py
aws_saml_auth/tests/test_configuration.py
aws_saml_auth/tests/test_configuration_persistence.py
aws_saml_auth/tests/test_init.py
aws_saml_auth/tests/test_python_version.py
aws_saml_auth/tests/test_util.py
aws_saml_auth-0.7.0.dist-info/LICENSE.txt
aws_saml_auth-0.7.0.dist-info/METADATA
aws_saml_auth-0.7.0.dist-info/WHEEL
aws_saml_auth-0.7.0.dist-info/entry_points.txt
aws_saml_auth-0.7.0.dist-info/top_level.txt
aws_saml_auth-0.7.0.dist-info/RECORD
