Metadata-Version: 2.1
Name: aws-saml-auth
Version: 0.7.0
Summary: Acquire AWS STS (temporary) credentials via SAML
Home-page: https://github.com/ekreative/aws-saml-auth
Author: Fred Cox
Author-email: fred@ekreative.com
License: MIT
Download-URL: https://github.com/ekreative/aws-saml-auth/archive/0.7.0.tar.gz
Keywords: saml sso federated identity google aws cli
Platform: UNKNOWN
Classifier: Development Status :: 4 - Beta
Classifier: Intended Audience :: Developers
Classifier: Intended Audience :: System Administrators
Classifier: Topic :: Security
Classifier: Topic :: System :: Systems Administration :: Authentication/Directory
Classifier: License :: OSI Approved :: MIT License
Classifier: Programming Language :: Python :: 2
Classifier: Programming Language :: Python :: 2.7
Classifier: Programming Language :: Python :: 3
Classifier: Programming Language :: Python :: 3.9
Requires-Dist: boto3
Requires-Dist: configparser
Requires-Dist: filelock
Requires-Dist: lxml
Requires-Dist: six
Requires-Dist: tabulate
Requires-Dist: tzlocal
Provides-Extra: test
Requires-Dist: nose ; extra == 'test'
Requires-Dist: mock ; extra == 'test'
